{
  "generated_at_utc": "2026-04-07T17:03:28.517006+00:00",
  "source_file": "RawData/Academxp20260407.mdb",
  "base_table": "CURSO_AL",
  "join_table": "GDRPESS",
  "required_fields": [
    "SIGLA_CURS",
    "STATUS",
    "D_ADIMISSA",
    "NIVEL"
  ],
  "recognized_program_codes": [
    "ISO",
    "PGAST",
    "PGCAP",
    "PGCST",
    "PGMET",
    "PGETE",
    "PGGES",
    "PGSER"
  ],
  "curso_al": {
    "records_total": 9158,
    "records_imported_success": 9117,
    "records_skipped_reg_aluno_invalido": 1,
    "records_skipped_sigla_curs_vazio": 23,
    "records_skipped_status_vazio": 0,
    "records_skipped_d_adimissa_vazio": 9,
    "records_skipped_d_adimissa_invalida": 2,
    "records_skipped_nivel_vazio": 4,
    "records_skipped_programa_nao_reconhecido": 2,
    "records_skipped_by_raw_program": {
      "ECOSDA": 1,
      "ECOTEC": 1
    },
    "records_by_programa_normalizado": {
      "ISO": 3496,
      "PGAST": 309,
      "PGCAP": 959,
      "PGCST": 175,
      "PGETE": 1600,
      "PGGES": 631,
      "PGMET": 876,
      "PGSER": 1071
    },
    "records_with_d_final": 3384,
    "records_with_d_situacao": 4254,
    "records_with_any_data_conclusao": 4264,
    "duplicate_reg_aluno": 0,
    "records_joined_with_gdrpess": 9117,
    "records_joined_without_gdrpess": 0
  },
  "gdrpess": {
    "records_total": 9225,
    "records_with_valid_reg_aluno": 9216,
    "records_with_nome": 9180,
    "records_skipped_reg_aluno_invalido": 9,
    "duplicate_reg_aluno": 0,
    "indexed_unique_reg_aluno": 9216
  },
  "output_file": "Data/alunos_lista.json"
}
